{
    "_gameObjects": [
        {
            "_objectType": "GAMEOBJECT",
            "_id": 1027,
            "_name": "",
            "_isActive": true,
            "_checkFrustum": true,
            "_layerIndex": 0,
            "_static": true,
            "_hash": 10837724395712690892,
            "_transform": {
                "_localTransform": {
                    "_position": {
                        "x": 0.0,
                        "y": 0.0,
                        "z": 0.0
                    },
                    "_rotation": {
                        "x": 0.0,
                        "y": 0.0,
                        "z": 0.0
                    },
                    "_scale": {
                        "x": 1.0,
                        "y": 1.0,
                        "z": 1.0
                    }
                },
                "_worldTransform": {
                    "_position": {
                        "x": 0.0,
                        "y": 0.0,
                        "z": 0.0
                    },
                    "_rotation": {
                        "x": 0.0,
                        "y": 0.0,
                        "z": 0.0
                    },
                    "_scale": {
                        "x": 1.0,
                        "y": 1.0,
                        "z": 1.0
                    }
                }
            },
            "_meshRenderer": {},
            "_camera": {},
            "_light": {},
            "_particleSystem": {},
            "_terrain": {},
            "_baseCollider": {},
            "_animator": {},
            "_scripts": []
        },
        {
            "_objectType": "GAMEOBJECT",
            "_id": 1028,
            "_name": "",
            "_isActive": true,
            "_checkFrustum": true,
            "_layerIndex": 0,
            "_static": true,
            "_hash": 5514151138106766407,
            "_transform": {
                "_localTransform": {
                    "_position": {
                        "x": 0.0,
                        "y": 0.0,
                        "z": 0.0
                    },
                    "_rotation": {
                        "x": 0.0,
                        "y": 0.0,
                        "z": 0.0
                    },
                    "_scale": {
                        "x": 1.0,
                        "y": 1.0,
                        "z": 1.0
                    }
                },
                "_worldTransform": {
                    "_position": {
                        "x": 0.0,
                        "y": 0.0,
                        "z": 0.0
                    },
                    "_rotation": {
                        "x": 0.0,
                        "y": 0.0,
                        "z": 0.0
                    },
                    "_scale": {
                        "x": 1.0,
                        "y": 1.0,
                        "z": 1.0
                    }
                }
            },
            "_meshRenderer": {},
            "_camera": {},
            "_light": {},
            "_particleSystem": {},
            "_terrain": {},
            "_baseCollider": {},
            "_animator": {},
            "_scripts": []
        },
        {
            "_objectType": "GAMEOBJECT",
            "_id": 908,
            "_name": "",
            "_isActive": true,
            "_checkFrustum": true,
            "_layerIndex": 0,
            "_static": true,
            "_hash": 15933270339916184171,
            "_transform": {
                "_localTransform": {
                    "_position": {
                        "x": 0.0,
                        "y": 0.0,
                        "z": 0.0
                    },
                    "_rotation": {
                        "x": 0.0,
                        "y": 0.0,
                        "z": 0.0
                    },
                    "_scale": {
                        "x": 1.0,
                        "y": 1.0,
                        "z": 1.0
                    }
                },
                "_worldTransform": {
                    "_position": {
                        "x": 0.0,
                        "y": 0.0,
                        "z": 0.0
                    },
                    "_rotation": {
                        "x": 0.0,
                        "y": 0.0,
                        "z": 0.0
                    },
                    "_scale": {
                        "x": 1.0,
                        "y": 1.0,
                        "z": 1.0
                    }
                }
            },
            "_meshRenderer": {
                "_materials": [
                    {
                        "_params": {
                            "intParams": [
                                0,
                                0,
                                0,
                                0
                            ],
                            "floatParams": [
                                0.0,
                                0.0,
                                0.0,
                                0.0
                            ],
                            "texOnParams": [
                                1,
                                1,
                                0,
                                0
                            ],
                            "vec2Params": [
                                {
                                    "x": 0.0,
                                    "y": 0.0
                                },
                                {
                                    "x": 0.0,
                                    "y": 0.0
                                },
                                {
                                    "x": 0.0,
                                    "y": 0.0
                                },
                                {
                                    "x": 0.0,
                                    "y": 0.0
                                }
                            ],
                            "vec4Params": [
                                {
                                    "x": 0.0,
                                    "y": 0.0,
                                    "z": 0.0,
                                    "w": 0.0
                                },
                                {
                                    "x": 0.0,
                                    "y": 0.0,
                                    "z": 0.0,
                                    "w": 0.0
                                },
                                {
                                    "x": 0.0,
                                    "y": 0.0,
                                    "z": 0.0,
                                    "w": 0.0
                                },
                                {
                                    "x": 0.0,
                                    "y": 0.0,
                                    "z": 0.0,
                                    "w": 0.0
                                }
                            ],
                            "matrixParams": [
                                {
                                    "m": [
                                        [
                                            1.0,
                                            0.0,
                                            0.0,
                                            0.0
                                        ],
                                        [
                                            0.0,
                                            1.0,
                                            0.0,
                                            0.0
                                        ],
                                        [
                                            0.0,
                                            0.0,
                                            1.0,
                                            0.0
                                        ],
                                        [
                                            0.0,
                                            0.0,
                                            0.0,
                                            1.0
                                        ]
                                    ]
                                },
                                {
                                    "m": [
                                        [
                                            1.0,
                                            0.0,
                                            0.0,
                                            0.0
                                        ],
                                        [
                                            0.0,
                                            1.0,
                                            0.0,
                                            0.0
                                        ],
                                        [
                                            0.0,
                                            0.0,
                                            1.0,
                                            0.0
                                        ],
                                        [
                                            0.0,
                                            0.0,
                                            0.0,
                                            1.0
                                        ]
                                    ]
                                },
                                {
                                    "m": [
                                        [
                                            1.0,
                                            0.0,
                                            0.0,
                                            0.0
                                        ],
                                        [
                                            0.0,
                                            1.0,
                                            0.0,
                                            0.0
                                        ],
                                        [
                                            0.0,
                                            0.0,
                                            1.0,
                                            0.0
                                        ],
                                        [
                                            0.0,
                                            0.0,
                                            0.0,
                                            1.0
                                        ]
                                    ]
                                },
                                {
                                    "m": [
                                        [
                                            1.0,
                                            0.0,
                                            0.0,
                                            0.0
                                        ],
                                        [
                                            0.0,
                                            1.0,
                                            0.0,
                                            0.0
                                        ],
                                        [
                                            0.0,
                                            0.0,
                                            1.0,
                                            0.0
                                        ],
                                        [
                                            0.0,
                                            0.0,
                                            0.0,
                                            1.0
                                        ]
                                    ]
                                }
                            ]
                        },
                        "_shader": {
                            "_objectType": "SHADER",
                            "_id": 12,
                            "_info": {
                                "shaderType": "DEFERRED",
                                "rasterizerType": "CULL_BACK",
                                "depthStencilType": "LESS",
                                "blendType": "DEFAULT",
                                "topology": 4
                            },
                            "_arg": {
                                "vs": "VS_Main",
                                "hs": "",
                                "ds": "",
                                "gs": "",
                                "ps": "PS_Main",
                                "cs": ""
                            },
                            "_name": ""
                        },
                        "_textures": [
                            {
                                "_objectType": "TEXTURE",
                                "_id": 703,
                                "_name": ""
                            },
                            {
                                "_objectType": "TEXTURE",
                                "_id": 704,
                                "_name": ""
                            },
                            {},
                            {}
                        ]
                    }
                ],
                "_mesh": {
                    "_objectType": "MESH",
                    "_id": 730,
                    "_name": ""
                }
            },
            "_camera": {},
            "_light": {},
            "_particleSystem": {},
            "_terrain": {},
            "_baseCollider": {},
            "_animator": {},
            "_scripts": []
        },
        {
            "_objectType": "GAMEOBJECT",
            "_id": 911,
            "_name": "",
            "_isActive": true,
            "_checkFrustum": true,
            "_layerIndex": 0,
            "_static": true,
            "_hash": 4759509248082469699,
            "_transform": {
                "_localTransform": {
                    "_position": {
                        "x": 0.0,
                        "y": 0.0,
                        "z": 0.0
                    },
                    "_rotation": {
                        "x": 0.0,
                        "y": 0.0,
                        "z": 0.0
                    },
                    "_scale": {
                        "x": 1.0,
                        "y": 1.0,
                        "z": 1.0
                    }
                },
                "_worldTransform": {
                    "_position": {
                        "x": 0.0,
                        "y": 0.0,
                        "z": 0.0
                    },
                    "_rotation": {
                        "x": 0.0,
                        "y": 0.0,
                        "z": 0.0
                    },
                    "_scale": {
                        "x": 1.0,
                        "y": 1.0,
                        "z": 1.0
                    }
                }
            },
            "_meshRenderer": {
                "_materials": [
                    {
                        "_params": {
                            "intParams": [
                                0,
                                0,
                                0,
                                0
                            ],
                            "floatParams": [
                                0.0,
                                0.0,
                                0.0,
                                0.0
                            ],
                            "texOnParams": [
                                1,
                                1,
                                0,
                                0
                            ],
                            "vec2Params": [
                                {
                                    "x": 0.0,
                                    "y": 0.0
                                },
                                {
                                    "x": 0.0,
                                    "y": 0.0
                                },
                                {
                                    "x": 0.0,
                                    "y": 0.0
                                },
                                {
                                    "x": 0.0,
                                    "y": 0.0
                                }
                            ],
                            "vec4Params": [
                                {
                                    "x": 0.0,
                                    "y": 0.0,
                                    "z": 0.0,
                                    "w": 0.0
                                },
                                {
                                    "x": 0.0,
                                    "y": 0.0,
                                    "z": 0.0,
                                    "w": 0.0
                                },
                                {
                                    "x": 0.0,
                                    "y": 0.0,
                                    "z": 0.0,
                                    "w": 0.0
                                },
                                {
                                    "x": 0.0,
                                    "y": 0.0,
                                    "z": 0.0,
                                    "w": 0.0
                                }
                            ],
                            "matrixParams": [
                                {
                                    "m": [
                                        [
                                            1.0,
                                            0.0,
                                            0.0,
                                            0.0
                                        ],
                                        [
                                            0.0,
                                            1.0,
                                            0.0,
                                            0.0
                                        ],
                                        [
                                            0.0,
                                            0.0,
                                            1.0,
                                            0.0
                                        ],
                                        [
                                            0.0,
                                            0.0,
                                            0.0,
                                            1.0
                                        ]
                                    ]
                                },
                                {
                                    "m": [
                                        [
                                            1.0,
                                            0.0,
                                            0.0,
                                            0.0
                                        ],
                                        [
                                            0.0,
                                            1.0,
                                            0.0,
                                            0.0
                                        ],
                                        [
                                            0.0,
                                            0.0,
                                            1.0,
                                            0.0
                                        ],
                                        [
                                            0.0,
                                            0.0,
                                            0.0,
                                            1.0
                                        ]
                                    ]
                                },
                                {
                                    "m": [
                                        [
                                            1.0,
                                            0.0,
                                            0.0,
                                            0.0
                                        ],
                                        [
                                            0.0,
                                            1.0,
                                            0.0,
                                            0.0
                                        ],
                                        [
                                            0.0,
                                            0.0,
                                            1.0,
                                            0.0
                                        ],
                                        [
                                            0.0,
                                            0.0,
                                            0.0,
                                            1.0
                                        ]
                                    ]
                                },
                                {
                                    "m": [
                                        [
                                            1.0,
                                            0.0,
                                            0.0,
                                            0.0
                                        ],
                                        [
                                            0.0,
                                            1.0,
                                            0.0,
                                            0.0
                                        ],
                                        [
                                            0.0,
                                            0.0,
                                            1.0,
                                            0.0
                                        ],
                                        [
                                            0.0,
                                            0.0,
                                            0.0,
                                            1.0
                                        ]
                                    ]
                                }
                            ]
                        },
                        "_shader": {
                            "_objectType": "SHADER",
                            "_id": 12,
                            "_info": {
                                "shaderType": "DEFERRED",
                                "rasterizerType": "CULL_BACK",
                                "depthStencilType": "LESS",
                                "blendType": "DEFAULT",
                                "topology": 4
                            },
                            "_arg": {
                                "vs": "VS_Main",
                                "hs": "",
                                "ds": "",
                                "gs": "",
                                "ps": "PS_Main",
                                "cs": ""
                            },
                            "_name": ""
                        },
                        "_textures": [
                            {
                                "_objectType": "TEXTURE",
                                "_id": 705,
                                "_name": ""
                            },
                            {
                                "_objectType": "TEXTURE",
                                "_id": 706,
                                "_name": ""
                            },
                            {},
                            {}
                        ]
                    }
                ],
                "_mesh": {
                    "_objectType": "MESH",
                    "_id": 731,
                    "_name": ""
                }
            },
            "_camera": {},
            "_light": {},
            "_particleSystem": {},
            "_terrain": {},
            "_baseCollider": {},
            "_animator": {},
            "_scripts": []
        },
        {
            "_objectType": "GAMEOBJECT",
            "_id": 914,
            "_name": "",
            "_isActive": true,
            "_checkFrustum": true,
            "_layerIndex": 0,
            "_static": true,
            "_hash": 2475411277930860667,
            "_transform": {
                "_localTransform": {
                    "_position": {
                        "x": 0.0,
                        "y": 0.0,
                        "z": 0.0
                    },
                    "_rotation": {
                        "x": 0.0,
                        "y": 0.0,
                        "z": 0.0
                    },
                    "_scale": {
                        "x": 1.0,
                        "y": 1.0,
                        "z": 1.0
                    }
                },
                "_worldTransform": {
                    "_position": {
                        "x": 0.0,
                        "y": 0.0,
                        "z": 0.0
                    },
                    "_rotation": {
                        "x": 0.0,
                        "y": 0.0,
                        "z": 0.0
                    },
                    "_scale": {
                        "x": 1.0,
                        "y": 1.0,
                        "z": 1.0
                    }
                }
            },
            "_meshRenderer": {
                "_materials": [
                    {
                        "_params": {
                            "intParams": [
                                0,
                                0,
                                0,
                                0
                            ],
                            "floatParams": [
                                0.0,
                                0.0,
                                0.0,
                                0.0
                            ],
                            "texOnParams": [
                                1,
                                1,
                                0,
                                0
                            ],
                            "vec2Params": [
                                {
                                    "x": 0.0,
                                    "y": 0.0
                                },
                                {
                                    "x": 0.0,
                                    "y": 0.0
                                },
                                {
                                    "x": 0.0,
                                    "y": 0.0
                                },
                                {
                                    "x": 0.0,
                                    "y": 0.0
                                }
                            ],
                            "vec4Params": [
                                {
                                    "x": 0.0,
                                    "y": 0.0,
                                    "z": 0.0,
                                    "w": 0.0
                                },
                                {
                                    "x": 0.0,
                                    "y": 0.0,
                                    "z": 0.0,
                                    "w": 0.0
                                },
                                {
                                    "x": 0.0,
                                    "y": 0.0,
                                    "z": 0.0,
                                    "w": 0.0
                                },
                                {
                                    "x": 0.0,
                                    "y": 0.0,
                                    "z": 0.0,
                                    "w": 0.0
                                }
                            ],
                            "matrixParams": [
                                {
                                    "m": [
                                        [
                                            1.0,
                                            0.0,
                                            0.0,
                                            0.0
                                        ],
                                        [
                                            0.0,
                                            1.0,
                                            0.0,
                                            0.0
                                        ],
                                        [
                                            0.0,
                                            0.0,
                                            1.0,
                                            0.0
                                        ],
                                        [
                                            0.0,
                                            0.0,
                                            0.0,
                                            1.0
                                        ]
                                    ]
                                },
                                {
                                    "m": [
                                        [
                                            1.0,
                                            0.0,
                                            0.0,
                                            0.0
                                        ],
                                        [
                                            0.0,
                                            1.0,
                                            0.0,
                                            0.0
                                        ],
                                        [
                                            0.0,
                                            0.0,
                                            1.0,
                                            0.0
                                        ],
                                        [
                                            0.0,
                                            0.0,
                                            0.0,
                                            1.0
                                        ]
                                    ]
                                },
                                {
                                    "m": [
                                        [
                                            1.0,
                                            0.0,
                                            0.0,
                                            0.0
                                        ],
                                        [
                                            0.0,
                                            1.0,
                                            0.0,
                                            0.0
                                        ],
                                        [
                                            0.0,
                                            0.0,
                                            1.0,
                                            0.0
                                        ],
                                        [
                                            0.0,
                                            0.0,
                                            0.0,
                                            1.0
                                        ]
                                    ]
                                },
                                {
                                    "m": [
                                        [
                                            1.0,
                                            0.0,
                                            0.0,
                                            0.0
                                        ],
                                        [
                                            0.0,
                                            1.0,
                                            0.0,
                                            0.0
                                        ],
                                        [
                                            0.0,
                                            0.0,
                                            1.0,
                                            0.0
                                        ],
                                        [
                                            0.0,
                                            0.0,
                                            0.0,
                                            1.0
                                        ]
                                    ]
                                }
                            ]
                        },
                        "_shader": {
                            "_objectType": "SHADER",
                            "_id": 12,
                            "_info": {
                                "shaderType": "DEFERRED",
                                "rasterizerType": "CULL_BACK",
                                "depthStencilType": "LESS",
                                "blendType": "DEFAULT",
                                "topology": 4
                            },
                            "_arg": {
                                "vs": "VS_Main",
                                "hs": "",
                                "ds": "",
                                "gs": "",
                                "ps": "PS_Main",
                                "cs": ""
                            },
                            "_name": ""
                        },
                        "_textures": [
                            {
                                "_objectType": "TEXTURE",
                                "_id": 707,
                                "_name": ""
                            },
                            {
                                "_objectType": "TEXTURE",
                                "_id": 708,
                                "_name": ""
                            },
                            {},
                            {}
                        ]
                    }
                ],
                "_mesh": {
                    "_objectType": "MESH",
                    "_id": 732,
                    "_name": ""
                }
            },
            "_camera": {},
            "_light": {},
            "_particleSystem": {},
            "_terrain": {},
            "_baseCollider": {},
            "_animator": {},
            "_scripts": []
        },
        {
            "_objectType": "GAMEOBJECT",
            "_id": 917,
            "_name": "",
            "_isActive": true,
            "_checkFrustum": true,
            "_layerIndex": 0,
            "_static": true,
            "_hash": 734975997975579091,
            "_transform": {
                "_localTransform": {
                    "_position": {
                        "x": 0.0,
                        "y": 0.0,
                        "z": 0.0
                    },
                    "_rotation": {
                        "x": 0.0,
                        "y": 0.0,
                        "z": 0.0
                    },
                    "_scale": {
                        "x": 1.0,
                        "y": 1.0,
                        "z": 1.0
                    }
                },
                "_worldTransform": {
                    "_position": {
                        "x": 0.0,
                        "y": 0.0,
                        "z": 0.0
                    },
                    "_rotation": {
                        "x": 0.0,
                        "y": 0.0,
                        "z": 0.0
                    },
                    "_scale": {
                        "x": 1.0,
                        "y": 1.0,
                        "z": 1.0
                    }
                }
            },
            "_meshRenderer": {
                "_materials": [
                    {
                        "_params": {
                            "intParams": [
                                0,
                                0,
                                0,
                                0
                            ],
                            "floatParams": [
                                0.0,
                                0.0,
                                0.0,
                                0.0
                            ],
                            "texOnParams": [
                                1,
                                1,
                                0,
                                0
                            ],
                            "vec2Params": [
                                {
                                    "x": 0.0,
                                    "y": 0.0
                                },
                                {
                                    "x": 0.0,
                                    "y": 0.0
                                },
                                {
                                    "x": 0.0,
                                    "y": 0.0
                                },
                                {
                                    "x": 0.0,
                                    "y": 0.0
                                }
                            ],
                            "vec4Params": [
                                {
                                    "x": 0.0,
                                    "y": 0.0,
                                    "z": 0.0,
                                    "w": 0.0
                                },
                                {
                                    "x": 0.0,
                                    "y": 0.0,
                                    "z": 0.0,
                                    "w": 0.0
                                },
                                {
                                    "x": 0.0,
                                    "y": 0.0,
                                    "z": 0.0,
                                    "w": 0.0
                                },
                                {
                                    "x": 0.0,
                                    "y": 0.0,
                                    "z": 0.0,
                                    "w": 0.0
                                }
                            ],
                            "matrixParams": [
                                {
                                    "m": [
                                        [
                                            1.0,
                                            0.0,
                                            0.0,
                                            0.0
                                        ],
                                        [
                                            0.0,
                                            1.0,
                                            0.0,
                                            0.0
                                        ],
                                        [
                                            0.0,
                                            0.0,
                                            1.0,
                                            0.0
                                        ],
                                        [
                                            0.0,
                                            0.0,
                                            0.0,
                                            1.0
                                        ]
                                    ]
                                },
                                {
                                    "m": [
                                        [
                                            1.0,
                                            0.0,
                                            0.0,
                                            0.0
                                        ],
                                        [
                                            0.0,
                                            1.0,
                                            0.0,
                                            0.0
                                        ],
                                        [
                                            0.0,
                                            0.0,
                                            1.0,
                                            0.0
                                        ],
                                        [
                                            0.0,
                                            0.0,
                                            0.0,
                                            1.0
                                        ]
                                    ]
                                },
                                {
                                    "m": [
                                        [
                                            1.0,
                                            0.0,
                                            0.0,
                                            0.0
                                        ],
                                        [
                                            0.0,
                                            1.0,
                                            0.0,
                                            0.0
                                        ],
                                        [
                                            0.0,
                                            0.0,
                                            1.0,
                                            0.0
                                        ],
                                        [
                                            0.0,
                                            0.0,
                                            0.0,
                                            1.0
                                        ]
                                    ]
                                },
                                {
                                    "m": [
                                        [
                                            1.0,
                                            0.0,
                                            0.0,
                                            0.0
                                        ],
                                        [
                                            0.0,
                                            1.0,
                                            0.0,
                                            0.0
                                        ],
                                        [
                                            0.0,
                                            0.0,
                                            1.0,
                                            0.0
                                        ],
                                        [
                                            0.0,
                                            0.0,
                                            0.0,
                                            1.0
                                        ]
                                    ]
                                }
                            ]
                        },
                        "_shader": {
                            "_objectType": "SHADER",
                            "_id": 12,
                            "_info": {
                                "shaderType": "DEFERRED",
                                "rasterizerType": "CULL_BACK",
                                "depthStencilType": "LESS",
                                "blendType": "DEFAULT",
                                "topology": 4
                            },
                            "_arg": {
                                "vs": "VS_Main",
                                "hs": "",
                                "ds": "",
                                "gs": "",
                                "ps": "PS_Main",
                                "cs": ""
                            },
                            "_name": ""
                        },
                        "_textures": [
                            {
                                "_objectType": "TEXTURE",
                                "_id": 709,
                                "_name": ""
                            },
                            {
                                "_objectType": "TEXTURE",
                                "_id": 710,
                                "_name": ""
                            },
                            {},
                            {}
                        ]
                    }
                ],
                "_mesh": {
                    "_objectType": "MESH",
                    "_id": 733,
                    "_name": ""
                }
            },
            "_camera": {},
            "_light": {},
            "_particleSystem": {},
            "_terrain": {},
            "_baseCollider": {},
            "_animator": {},
            "_scripts": []
        },
        {
            "_objectType": "GAMEOBJECT",
            "_id": 920,
            "_name": "",
            "_isActive": true,
            "_checkFrustum": true,
            "_layerIndex": 0,
            "_static": true,
            "_hash": 18101272912182505803,
            "_transform": {
                "_localTransform": {
                    "_position": {
                        "x": 0.0,
                        "y": 0.0,
                        "z": 0.0
                    },
                    "_rotation": {
                        "x": 0.0,
                        "y": 0.0,
                        "z": 0.0
                    },
                    "_scale": {
                        "x": 1.0,
                        "y": 1.0,
                        "z": 1.0
                    }
                },
                "_worldTransform": {
                    "_position": {
                        "x": 0.0,
                        "y": 0.0,
                        "z": 0.0
                    },
                    "_rotation": {
                        "x": 0.0,
                        "y": 0.0,
                        "z": 0.0
                    },
                    "_scale": {
                        "x": 1.0,
                        "y": 1.0,
                        "z": 1.0
                    }
                }
            },
            "_meshRenderer": {
                "_materials": [
                    {
                        "_params": {
                            "intParams": [
                                0,
                                0,
                                0,
                                0
                            ],
                            "floatParams": [
                                0.0,
                                0.0,
                                0.0,
                                0.0
                            ],
                            "texOnParams": [
                                1,
                                1,
                                0,
                                0
                            ],
                            "vec2Params": [
                                {
                                    "x": 0.0,
                                    "y": 0.0
                                },
                                {
                                    "x": 0.0,
                                    "y": 0.0
                                },
                                {
                                    "x": 0.0,
                                    "y": 0.0
                                },
                                {
                                    "x": 0.0,
                                    "y": 0.0
                                }
                            ],
                            "vec4Params": [
                                {
                                    "x": 0.0,
                                    "y": 0.0,
                                    "z": 0.0,
                                    "w": 0.0
                                },
                                {
                                    "x": 0.0,
                                    "y": 0.0,
                                    "z": 0.0,
                                    "w": 0.0
                                },
                                {
                                    "x": 0.0,
                                    "y": 0.0,
                                    "z": 0.0,
                                    "w": 0.0
                                },
                                {
                                    "x": 0.0,
                                    "y": 0.0,
                                    "z": 0.0,
                                    "w": 0.0
                                }
                            ],
                            "matrixParams": [
                                {
                                    "m": [
                                        [
                                            1.0,
                                            0.0,
                                            0.0,
                                            0.0
                                        ],
                                        [
                                            0.0,
                                            1.0,
                                            0.0,
                                            0.0
                                        ],
                                        [
                                            0.0,
                                            0.0,
                                            1.0,
                                            0.0
                                        ],
                                        [
                                            0.0,
                                            0.0,
                                            0.0,
                                            1.0
                                        ]
                                    ]
                                },
                                {
                                    "m": [
                                        [
                                            1.0,
                                            0.0,
                                            0.0,
                                            0.0
                                        ],
                                        [
                                            0.0,
                                            1.0,
                                            0.0,
                                            0.0
                                        ],
                                        [
                                            0.0,
                                            0.0,
                                            1.0,
                                            0.0
                                        ],
                                        [
                                            0.0,
                                            0.0,
                                            0.0,
                                            1.0
                                        ]
                                    ]
                                },
                                {
                                    "m": [
                                        [
                                            1.0,
                                            0.0,
                                            0.0,
                                            0.0
                                        ],
                                        [
                                            0.0,
                                            1.0,
                                            0.0,
                                            0.0
                                        ],
                                        [
                                            0.0,
                                            0.0,
                                            1.0,
                                            0.0
                                        ],
                                        [
                                            0.0,
                                            0.0,
                                            0.0,
                                            1.0
                                        ]
                                    ]
                                },
                                {
                                    "m": [
                                        [
                                            1.0,
                                            0.0,
                                            0.0,
                                            0.0
                                        ],
                                        [
                                            0.0,
                                            1.0,
                                            0.0,
                                            0.0
                                        ],
                                        [
                                            0.0,
                                            0.0,
                                            1.0,
                                            0.0
                                        ],
                                        [
                                            0.0,
                                            0.0,
                                            0.0,
                                            1.0
                                        ]
                                    ]
                                }
                            ]
                        },
                        "_shader": {
                            "_objectType": "SHADER",
                            "_id": 12,
                            "_info": {
                                "shaderType": "DEFERRED",
                                "rasterizerType": "CULL_BACK",
                                "depthStencilType": "LESS",
                                "blendType": "DEFAULT",
                                "topology": 4
                            },
                            "_arg": {
                                "vs": "VS_Main",
                                "hs": "",
                                "ds": "",
                                "gs": "",
                                "ps": "PS_Main",
                                "cs": ""
                            },
                            "_name": ""
                        },
                        "_textures": [
                            {
                                "_objectType": "TEXTURE",
                                "_id": 711,
                                "_name": ""
                            },
                            {
                                "_objectType": "TEXTURE",
                                "_id": 712,
                                "_name": ""
                            },
                            {},
                            {}
                        ]
                    }
                ],
                "_mesh": {
                    "_objectType": "MESH",
                    "_id": 734,
                    "_name": ""
                }
            },
            "_camera": {},
            "_light": {},
            "_particleSystem": {},
            "_terrain": {},
            "_baseCollider": {},
            "_animator": {},
            "_scripts": []
        }
    ],
    "_cameras": [],
    "_lights": []
}